<annotation>
	<folder></folder>
	<filename>18-Acquisition-20063790-0_phase_png.rf.dcd8b22c0b066e8fcaba2d53fe1818af.jpg</filename>
	<path>18-Acquisition-20063790-0_phase_png.rf.dcd8b22c0b066e8fcaba2d53fe1818af.jpg</path>
	<source>
		<database>roboflow.ai</database>
	</source>
	<size>
		<width>1624</width>
		<height>1224</height>
		<depth>3</depth>
	</size>
	<segmented>0</segmented>
	<object>
		<name>cell</name>
		<pose>Unspecified</pose>
		<truncated>0</truncated>
		<difficult>0</difficult>
		<occluded>0</occluded>
		<bndbox>
			<xmin>914</xmin>
			<xmax>1152</xmax>
			<ymin>864</ymin>
			<ymax>1099</ymax>
		</bndbox>
	</object>
	<object>
		<name>cell</name>
		<pose>Unspecified</pose>
		<truncated>0</truncated>
		<difficult>0</difficult>
		<occluded>0</occluded>
		<bndbox>
			<xmin>375</xmin>
			<xmax>617</xmax>
			<ymin>360</ymin>
			<ymax>644</ymax>
		</bndbox>
	</object>
</annotation>
